Metadata-Version: 2.1
Name: leonranp-LeonMMcoset
Version: 0.0.1
Summary: This is Leon Random Plus,that add more functions to the random!
Home-page: 
Author: LeonMMcoset
Author-email: leonmmcoset@outlook.com
Classifier: Programming Language :: Python :: 3
Classifier: License :: OSI Approved :: MIT License
Classifier: Operating System :: OS Independent
Requires-Python: >=3.6
License-File: LICENSE.txt
